nagisa_bert/__init__.py
nagisa_bert/tokenization_nagisa_bert.py
tests/__init__.py
tests/test_tokenization_nagisa_bert.py
nagisa_bert-0.0.4.dist-info/LICENSE
nagisa_bert-0.0.4.dist-info/METADATA
nagisa_bert-0.0.4.dist-info/WHEEL
nagisa_bert-0.0.4.dist-info/top_level.txt
nagisa_bert-0.0.4.dist-info/RECORD
