Metadata-Version: 2.1
Name: nagisa-bert
Version: 0.0.4
Summary: A BERT model for nagisa
Home-page: https://github.com/taishi-i/nagisa_bert
Author: taishi-i
Author-email: taishi.ikeda.0323@gmail.com
Maintainer: taishi-i
Maintainer-email: taishi.ikeda.0323@gmail.com
License: MIT
Keywords: NLP,BERT,Transformers,Japanese
Platform: UNKNOWN
Classifier: License :: OSI Approved :: MIT License
Classifier: Programming Language :: Python :: 3
Classifier: Programming Language :: Python :: 3.7
Classifier: Programming Language :: Python :: 3.8
Classifier: Programming Language :: Python :: 3.9
Classifier: Programming Language :: Python :: 3.10
Classifier: Topic :: Software Development :: Libraries :: Python Modules
Classifier: Natural Language :: Japanese
Requires-Python: >=3.7
Requires-Dist: nagisa
Requires-Dist: transformers
